dstate/__init__.py
dstate/driver/__init__.py
dstate/driver/dummy.py
dstate/driver/pymongo.py
dstate-0.1.0.dist-info/LICENSE
dstate-0.1.0.dist-info/WHEEL
dstate-0.1.0.dist-info/METADATA
dstate-0.1.0.dist-info/RECORD
