Metadata-Version: 2.1
Name: dstate
Version: 0.1.0
Summary: dstate is the library for distributed finite state machines
License: MIT
Author: Alex Ptakhin
Author-email: me@aptakhin.name
Requires-Python: >=3.9,<4.0
Classifier: License :: OSI Approved :: MIT License
Classifier: Programming Language :: Python :: 3
Classifier: Programming Language :: Python :: 3.9
Classifier: Programming Language :: Python :: 3.10
Classifier: Programming Language :: Python :: 3.11
